<?xml version="1.0" encoding="UTF-8"?>

<PropertyList>

  <sim>
    <model>
      <livery>
        <name type="string">Default</name>
     <texture-fuselage>Liveries/default/mainfuselage.png</texture-fuselage>
     <texture-fuselagetop>Liveries/default/fuselage-top.png</texture-fuselagetop>
	 <texture-nose>Liveries/default/nose.png</texture-nose>
	 <texture-fuselagerear>Liveries/default/tail.png</texture-fuselagerear>
    <texture-upperwings>Liveries/test/wings_top.png</texture-upperwings>
	 <texture-lwings>Liveries/default/wings_bottom.png</texture-lwings>
	 <texture-tanks>Liveries/default/tank.png</texture-tanks>
     <texture-gear>Liveries/default/Gear1.png</texture-gear>
	  <texture-fuselagebottom>Liveries/default/fuselagelow.png</texture-fuselagebottom>

   <specular>
              <red>   0.3 </red>
              <green> 0.3 </green>
              <blue>  0.3 </blue>
            </specular>

            <emission>
              <red>   0.2 </red>
              <green> 0.2 </green>
              <blue>  0.2 </blue>
            </emission>

      </livery>
    </model>
  </sim>

</PropertyList>
